aurora_rgbmatrix/__init__.py
aurora_renderer_rgbmatrix-1.0.0.dev20220104211843.dist-info/LICENSE
aurora_renderer_rgbmatrix-1.0.0.dev20220104211843.dist-info/METADATA
aurora_renderer_rgbmatrix-1.0.0.dev20220104211843.dist-info/WHEEL
aurora_renderer_rgbmatrix-1.0.0.dev20220104211843.dist-info/top_level.txt
aurora_renderer_rgbmatrix-1.0.0.dev20220104211843.dist-info/RECORD
